video_quick_editor_mcp/__init__.py
video_quick_editor_mcp/main.py
video_quick_editor_mcp-0.2.6.dist-info/METADATA
video_quick_editor_mcp-0.2.6.dist-info/WHEEL
video_quick_editor_mcp-0.2.6.dist-info/entry_points.txt
video_quick_editor_mcp-0.2.6.dist-info/RECORD
